mend_import_sbom/__init__.py
mend_import_sbom/_version.py
mend_import_sbom/conftest.py
mend_import_sbom/import_const.py
mend_import_sbom/import_sbom.py
mend_import_sbom-23.11.1.dist-info/LICENSE
mend_import_sbom-23.11.1.dist-info/METADATA
mend_import_sbom-23.11.1.dist-info/WHEEL
mend_import_sbom-23.11.1.dist-info/entry_points.txt
mend_import_sbom-23.11.1.dist-info/top_level.txt
mend_import_sbom-23.11.1.dist-info/RECORD
