Metadata-Version: 2.1
Name: mend-import-sbom
Version: 23.11.1
Summary: Import SPDX or CSV SBOM into Mend
Home-page: https://github.com/mend-toolkit/import-sbom
Author: Mend Professional Services
Author-email: ps@mend.io
License: LICENSE.txt
Classifier: Programming Language :: Python :: 3.9
Classifier: Programming Language :: Python :: 3.10
Classifier: Programming Language :: Python :: 3.11
Classifier: License :: OSI Approved :: Apache Software License
Classifier: Operating System :: OS Independent
Requires-Python: >=3.9
License-File: LICENSE
Requires-Dist: setuptools ~=65.5.1
Requires-Dist: DateTime ~=4.9
Requires-Dist: requests ~=2.31.0
